Workbook

Sheet Tabla de precios
A1: Tabla de precios de impresión
A2: Impresora Ricoh MP C3003 · precio por hoja · tamaño carta y oficio · septiembre de 2026
A4: Rango | B4: ¿Qué tipo de hoja es? | C4: Nos cuesta (aprox.) | D4: Se cobra | E4: Para mantenimiento | F4: Ganancia
A5: BLANCO Y NEGRO
A6: B/N normal | B6: Texto, tareas, cartas, formularios | C6: =Desglose!G5 -> 40.35 | D6: =Desglose!I5 -> 700 | E6: =Desglose!K5 -> 329.825 | F6: =Desglose!L5 -> 329.825
A7: B/N cargado | B7: Tablas oscuras, gráficas o fotos en gris | C7: =Desglose!G6 -> 68.442857 | D7: =Desglose!I6 -> 700 | E7: =Desglose!K6 -> 315.77857 | F7: =Desglose!L6 -> 315.77857
A8: B/N total | B8: Foto en gris a página completa, fondos negros | C8: =Desglose!G7 -> 133.5 | D8: =Desglose!I7 -> 700 | E8: =Desglose!K7 -> 283.25 | F8: =Desglose!L7 -> 283.25
A10: COLOR
A11: Color mínimo | B11: Documento con título, logo o firma a color | C11: =Desglose!G8 -> 56.660672 | D11: =Desglose!I8 -> 1000 | E11: =Desglose!K8 -> 471.66966 | F11: =Desglose!L8 -> 471.66966
A12: Color medio | B12: Una foto o imagen de media página | C12: =Desglose!G9 -> 162.77668 | D12: =Desglose!I9 -> 2000 | E12: =Desglose!K9 -> 918.61166 | F12: =Desglose!L9 -> 918.61166
A13: Color alto | B13: Dos fotos o una imagen grande | C13: =Desglose!G10 -> 295.82395 | D13: =Desglose!I10 -> 3000 | E13: =Desglose!K10 -> 1352.088 | F13: =Desglose!L10 -> 1352.088
A14: Color total | B14: Foto o afiche a página completa | C14: =Desglose!G11 -> 408.84189 | D14: =Desglose!I11 -> 4000 | E14: =Desglose!K11 -> 1795.5791 | F14: =Desglose!L11 -> 1795.5791
A16: ¿Cuánto deja un tóner?
A17: Ejemplo | C17: Hojas | D17: Se vende | E17: Para mantenimiento | F17: Ganancia
A18: Un tóner negro gastado en hojas de texto (B/N normal) | C18: =Desglose!C17 -> 17391.304 | D18: =Desglose!D17 -> 12173913 | E18: =Desglose!F17 -> 5736087 | F18: =Desglose!G17 -> 5736087
A19: Un tóner de color gastado en hojas con una foto (Color medio) | C19: =Desglose!C21 -> 1506.2886 | D19: =Desglose!D21 -> 3012577.2 | E19: =Desglose!F21 -> 1383694.3 | F19: =Desglose!G21 -> 1383694.3
A21: Notas
A22: 1. El programa revisa cada hoja y la pone sola en su rango según la tinta que usa. Si el trabajo tiene varias hojas, muestra cuántas hay de cada rango y el total.
A23: 2. "Nos cuesta" incluye la tinta (con 15 % extra por seguridad) y el papel de una hoja típica del rango. No incluye arriendo, luz ni el tiempo de trabajo.
A24: 3. Blanco y negro se cobra $700 en los tres rangos. Los rangos se muestran para que se vea que una hoja de texto cuesta muy poco y que incluso una hoja casi toda negra sigue dejando buena ganancia.
A25: 4. Color va de $1.000 a $4.000 según cuánta hoja ocupe el color. Una hoja de texto con un título o logo a color ya cuenta como color (rango mínimo).
A26: 5. Lo que sobra después de pagar tinta y papel se reparte mitad para mantenimiento (tambores, fusor, técnico, imprevistos) y mitad ganancia. Se sugiere guardar la parte de mantenimiento aparte.
A27: 6. Oficio se cobra igual que carta. Una hoja oficio gasta cerca de 18 % más tinta y el papel cuesta $38 en vez de $30; como se vende poco y el margen es amplio, no vale la pena cobrarla distinto.
A28: 7. Aun la hoja más cargada de cada rango queda cubierta por su precio (ver hoja Desglose, columna "Costo máximo").
A29: 8. Precios de tóner y papel de septiembre de 2026. Si cambian, se actualizan en la hoja Supuestos y toda la tabla se recalcula sola.

Sheet Supuestos
A1: Supuestos del cálculo
A2: Celdas en azul con fondo amarillo = datos que se pueden cambiar. Todo lo demás se recalcula solo.
A4: Tóner
A5: Precio de un tóner de color (C, M o Y) | B5: 200000 | C5: Dato de Felipe, sep. 2026
A6: Rendimiento tóner de color (hojas al 5 %) | B6: 17000 | C6: Estimado de Felipe
A7: Precio del tóner negro (K) | B7: 180000 | C7: Dato de Felipe, sep. 2026
A8: Rendimiento tóner negro (hojas al 5 %) | B8: 28000 | C8: Estimado de Felipe
A9: Cobertura con que se mide el rendimiento | B9: 0.05 | C9: Norma de los fabricantes
A10: Factor de corrección (seguridad en tinta) | B10: 1.15 | C10: 1,15 = se asume 15 % más tinta de la calculada
A11: Papel
A12: Resma carta | B12: 15000 | C12: Dato de Felipe
A13: Resma oficio | B13: 19000 | C13: Dato de Felipe
A14: Hojas por resma | B14: 500 | C14: Dato de Felipe
A15: Alto hoja carta (mm) | B15: 279.4 | C15: Mismo ancho que oficio (215,9 mm)
A16: Alto hoja oficio (mm) | B16: 330.2 | C16: Oficio 21,6 × 33 cm
A17: Reparto de lo que sobra
A18: Parte para capital (mantenimiento e imprevistos) | B18: 0.5 | C18: Propuesta de Felipe: mitad y mitad
A19: Desgaste estimado por hoja a color | B19: 40 | C19: Estimado: tambores, revelador, fusor
A20: Desgaste estimado por hoja b/n | B20: 20 | C20: Estimado
A22: Valores calculados
A23: Costo de tinta de color por hoja carta al 100 % | B23: =Supuestos!$B$5/Supuestos!$B$6/Supuestos!$B$9 -> 235.29412 | C23: precio ÷ rendimiento ÷ 5 %
A24: Costo de tinta negra por hoja carta al 100 % | B24: =Supuestos!$B$7/Supuestos!$B$8/Supuestos!$B$9 -> 128.57143 | C24: precio ÷ rendimiento ÷ 5 %
A25: Papel por hoja carta | B25: =Supuestos!$B$12/Supuestos!$B$14 -> 30
A26: Papel por hoja oficio | B26: =Supuestos!$B$13/Supuestos!$B$14 -> 38
A27: Área oficio ÷ área carta | B27: =Supuestos!$B$16/Supuestos!$B$15 -> 1.1818182 | C27: la tinta crece con el área

Sheet Desglose
A1: Desglose de costos por rango (hoja carta)
A2: Azul = dato editable. Negro = fórmula. Verde = viene de la hoja Supuestos. Cobertura típica medida con páginas de referencia; límite = máximo del rango en el programa.
A4: Rango | B4: Cobertura típica color (C+M+Y) | C4: Cobertura típica negro (K) | D4: Límite de cobertura del rango | E4: Tinta por hoja (típica) | F4: Papel por hoja | G4: Costo aproximado (tinta + papel) | H4: Costo máximo del rango | I4: Precio de venta | J4: Sobrante (venta − costo) | K4: Para capital | L4: Ganancia | M4: Desgaste estimado | N4: ¿El capital cubre el desgaste? | O4: Costo aproximado en oficio | P4: Ganancia en oficio
A5: B/N normal | B5: 0 | C5: 0.07 | D5: 0.12 | E5: =(B5*Supuestos!$B$23+C5*Supuestos!$B$24)*Supuestos!$B$10 -> 10.35 | F5: =Supuestos!$B$25 -> 30 | G5: =E5+F5 -> 40.35 | H5: =D5*Supuestos!$B$24*Supuestos!$B$10+F5 -> 47.742857 | I5: 700 | J5: =I5-G5 -> 659.65 | K5: =J5*Supuestos!$B$18 -> 329.825 | L5: =J5-K5 -> 329.825 | M5: =Supuestos!$B$20 -> 20 | N5: =IF(K5>=M5,"Sí","No") -> Sí | O5: =E5*Supuestos!$B$27+Supuestos!$B$26 -> 50.231818 | P5: =(I5-O5)*(1-Supuestos!$B$18) -> 324.88409
A6: B/N cargado | B6: 0 | C6: 0.26 | D6: 0.4 | E6: =(B6*Supuestos!$B$23+C6*Supuestos!$B$24)*Supuestos!$B$10 -> 38.442857 | F6: =Supuestos!$B$25 -> 30 | G6: =E6+F6 -> 68.442857 | H6: =D6*Supuestos!$B$24*Supuestos!$B$10+F6 -> 89.142857 | I6: 700 | J6: =I6-G6 -> 631.55714 | K6: =J6*Supuestos!$B$18 -> 315.77857 | L6: =J6-K6 -> 315.77857 | M6: =Supuestos!$B$20 -> 20 | N6: =IF(K6>=M6,"Sí","No") -> Sí | O6: =E6*Supuestos!$B$27+Supuestos!$B$26 -> 83.432468 | P6: =(I6-O6)*(1-Supuestos!$B$18) -> 308.28377
A7: B/N total | B7: 0 | C7: 0.7 | D7: 1 | E7: =(B7*Supuestos!$B$23+C7*Supuestos!$B$24)*Supuestos!$B$10 -> 103.5 | F7: =Supuestos!$B$25 -> 30 | G7: =E7+F7 -> 133.5 | H7: =D7*Supuestos!$B$24*Supuestos!$B$10+F7 -> 177.85714 | I7: 700 | J7: =I7-G7 -> 566.5 | K7: =J7*Supuestos!$B$18 -> 283.25 | L7: =J7-K7 -> 283.25 | M7: =Supuestos!$B$20 -> 20 | N7: =IF(K7>=M7,"Sí","No") -> Sí | O7: =E7*Supuestos!$B$27+Supuestos!$B$26 -> 160.31818 | P7: =(I7-O7)*(1-Supuestos!$B$18) -> 269.84091
A8: Color mínimo | B8: 0.057 | C8: 0.076 | D8: 0.2 | E8: =(B8*Supuestos!$B$23+C8*Supuestos!$B$24)*Supuestos!$B$10 -> 26.660672 | F8: =Supuestos!$B$25 -> 30 | G8: =E8+F8 -> 56.660672 | H8: =D8*Supuestos!$B$23*Supuestos!$B$10+F8 -> 84.117647 | I8: 1000 | J8: =I8-G8 -> 943.33933 | K8: =J8*Supuestos!$B$18 -> 471.66966 | L8: =J8-K8 -> 471.66966 | M8: =Supuestos!$B$19 -> 40 | N8: =IF(K8>=M8,"Sí","No") -> Sí | O8: =E8*Supuestos!$B$27+Supuestos!$B$26 -> 69.508067 | P8: =(I8-O8)*(1-Supuestos!$B$18) -> 465.24597
A9: Color medio | B9: 0.406 | C9: 0.155 | D9: 0.8 | E9: =(B9*Supuestos!$B$23+C9*Supuestos!$B$24)*Supuestos!$B$10 -> 132.77668 | F9: =Supuestos!$B$25 -> 30 | G9: =E9+F9 -> 162.77668 | H9: =D9*Supuestos!$B$23*Supuestos!$B$10+F9 -> 246.47059 | I9: 2000 | J9: =I9-G9 -> 1837.2233 | K9: =J9*Supuestos!$B$18 -> 918.61166 | L9: =J9-K9 -> 918.61166 | M9: =Supuestos!$B$19 -> 40 | N9: =IF(K9>=M9,"Sí","No") -> Sí | O9: =E9*Supuestos!$B$27+Supuestos!$B$26 -> 194.9179 | P9: =(I9-O9)*(1-Supuestos!$B$18) -> 902.54105
A10: Color alto | B10: 0.813 | C10: 0.31 | D10: 1.4 | E10: =(B10*Supuestos!$B$23+C10*Supuestos!$B$24)*Supuestos!$B$10 -> 265.82395 | F10: =Supuestos!$B$25 -> 30 | G10: =E10+F10 -> 295.82395 | H10: =D10*Supuestos!$B$23*Supuestos!$B$10+F10 -> 408.82353 | I10: 3000 | J10: =I10-G10 -> 2704.1761 | K10: =J10*Supuestos!$B$18 -> 1352.088 | L10: =J10-K10 -> 1352.088 | M10: =Supuestos!$B$19 -> 40 | N10: =IF(K10>=M10,"Sí","No") -> Sí | O10: =E10*Supuestos!$B$27+Supuestos!$B$26 -> 352.15558 | P10: =(I10-O10)*(1-Supuestos!$B$18) -> 1323.9222
A11: Color total | B11: 1.158 | C11: 0.443 | D11: 2.5 | E11: =(B11*Supuestos!$B$23+C11*Supuestos!$B$24)*Supuestos!$B$10 -> 378.84189 | F11: =Supuestos!$B$25 -> 30 | G11: =E11+F11 -> 408.84189 | H11: =D11*Supuestos!$B$23*Supuestos!$B$10+F11 -> 706.47059 | I11: 4000 | J11: =I11-G11 -> 3591.1581 | K11: =J11*Supuestos!$B$18 -> 1795.5791 | L11: =J11-K11 -> 1795.5791 | M11: =Supuestos!$B$19 -> 40 | N11: =IF(K11>=M11,"Sí","No") -> Sí | O11: =E11*Supuestos!$B$27+Supuestos!$B$26 -> 485.72223 | P11: =(I11-O11)*(1-Supuestos!$B$18) -> 1757.1389
A14: ¿Cuánto deja cada tóner?
A15: Si todo el tóner se gastara en hojas de un solo rango: cuántas hojas alcanza a pagar la tinta de un tóner, y cuánto entra por ellas. Incluye el factor de corrección.
A16: Rango | B16: Precio de un tóner | C16: Hojas que paga ese tóner | D16: Ventas | E16: Gasto en papel | F16: Para capital | G16: Ganancia
A17: =A5 -> B/N normal | B17: =Supuestos!$B$7 -> 180000 | C17: =B17/E5 -> 17391.304 | D17: =C17*I5 -> 12173913 | E17: =C17*F5 -> 521739.13 | F17: =C17*K5 -> 5736087 | G17: =C17*L5 -> 5736087
A18: =A6 -> B/N cargado | B18: =Supuestos!$B$7 -> 180000 | C18: =B18/E6 -> 4682.2742 | D18: =C18*I6 -> 3277592 | E18: =C18*F6 -> 140468.23 | F18: =C18*K6 -> 1478561.9 | G18: =C18*L6 -> 1478561.9
A19: =A7 -> B/N total | B19: =Supuestos!$B$7 -> 180000 | C19: =B19/E7 -> 1739.1304 | D19: =C19*I7 -> 1217391.3 | E19: =C19*F7 -> 52173.913 | F19: =C19*K7 -> 492608.7 | G19: =C19*L7 -> 492608.7
A20: =A8 -> Color mínimo | B20: =Supuestos!$B$5 -> 200000 | C20: =B20/E8 -> 7501.6863 | D20: =C20*I8 -> 7501686.3 | E20: =C20*F8 -> 225050.59 | F20: =C20*K8 -> 3538317.9 | G20: =C20*L8 -> 3538317.9
A21: =A9 -> Color medio | B21: =Supuestos!$B$5 -> 200000 | C21: =B21/E9 -> 1506.2886 | D21: =C21*I9 -> 3012577.2 | E21: =C21*F9 -> 45188.658 | F21: =C21*K9 -> 1383694.3 | G21: =C21*L9 -> 1383694.3
A22: =A10 -> Color alto | B22: =Supuestos!$B$5 -> 200000 | C22: =B22/E10 -> 752.37766 | D22: =C22*I10 -> 2257133 | E22: =C22*F10 -> 22571.33 | F22: =C22*K10 -> 1017280.8 | G22: =C22*L10 -> 1017280.8
A23: =A11 -> Color total | B23: =Supuestos!$B$5 -> 200000 | C23: =B23/E11 -> 527.92472 | D23: =C23*I11 -> 2111698.9 | E23: =C23*F11 -> 15837.742 | F23: =C23*K11 -> 947930.57 | G23: =C23*L11 -> 947930.57
A25: Cómo leer esta tabla:
A26: • Tinta por hoja = (precio del tóner ÷ rendimiento) × (cobertura ÷ 5 %) × factor de corrección.
A27: • Sobrante = precio de venta − tinta − papel. Se reparte entre capital y ganancia según el % de la hoja Supuestos.
A28: • El desgaste (tambores, fusor) NO se resta aparte: se paga del capital. La columna N verifica que alcance.
A29: • Tóner: una hoja a color también gasta algo de negro; aquí se cuenta toda la tinta de la hoja contra un tóner.
A30: • No incluye arriendo, energía ni el tiempo de trabajo.
